setup.py
salure_helpers/sap/__init__.py
salure_helpers/sap/base_functions.py
salure_helpers/sap/delimit_endpoints.py
salure_helpers/sap/get_endpoints.py
salure_helpers/sap/post_endpoints.py
salure_helpers/sap/sap.py
salure_helpers_sap.egg-info/PKG-INFO
salure_helpers_sap.egg-info/SOURCES.txt
salure_helpers_sap.egg-info/dependency_links.txt
salure_helpers_sap.egg-info/not-zip-safe
salure_helpers_sap.egg-info/requires.txt
salure_helpers_sap.egg-info/top_level.txt