Metadata-Version: 1.0
Name: salure-helpers-sap
Version: 1.5.6
Summary: SAP wrapper from Salure
Home-page: UNKNOWN
Author: D&A Salure
Author-email: support@salureconnnect.com
License: Salure License
Platform: UNKNOWN
